risclog.sqlalchemy-7.2-py3.9-nspkg.pth
risclog/sqlalchemy/__init__.py
risclog/sqlalchemy/cache.py
risclog/sqlalchemy/db.py
risclog/sqlalchemy/fixtures.py
risclog/sqlalchemy/functions.py
risclog/sqlalchemy/interfaces.py
risclog/sqlalchemy/model.py
risclog/sqlalchemy/serializer.py
risclog/sqlalchemy/testing.py
risclog/sqlalchemy/testlayer.py
risclog/sqlalchemy/tests/__init__.py
risclog/sqlalchemy/tests/conftest.py
risclog/sqlalchemy/tests/test_cache.py
risclog/sqlalchemy/tests/test_db.py
risclog/sqlalchemy/tests/test_fixtures.py
risclog/sqlalchemy/tests/test_model.py
risclog/sqlalchemy/tests/test_serializer.py
risclog/sqlalchemy/tests/fixtures/alembic/env.py
risclog/sqlalchemy/tests/fixtures/alembic/script.py.mako
risclog/sqlalchemy/tests/fixtures/alembic/versions/3f735078d5a8_foo.py
risclog.sqlalchemy-7.2.data/data/CHANGES.rst
risclog.sqlalchemy-7.2.data/data/COPYRIGHT.rst
risclog.sqlalchemy-7.2.data/data/HACKING.rst
risclog.sqlalchemy-7.2.data/data/README.rst
risclog.sqlalchemy-7.2.dist-info/LICENSE.txt
risclog.sqlalchemy-7.2.dist-info/METADATA
risclog.sqlalchemy-7.2.dist-info/WHEEL
risclog.sqlalchemy-7.2.dist-info/namespace_packages.txt
risclog.sqlalchemy-7.2.dist-info/top_level.txt
risclog.sqlalchemy-7.2.dist-info/RECORD
