Metadata-Version: 2.1
Name: risclog.sqlalchemy
Version: 7.2
Summary: Encapsulate sqlalchemy modelling infrastructure.
Home-page: https://github.com/gocept/risclog.sqlalchemy
Author: gocept <mail@gocept.com>
Author-email: mail@gocept.com
License: ZPL 2.1
Keywords: sqlalchemy alembic model infrastructure utility
Classifier: Development Status :: 5 - Production/Stable
Classifier: Framework :: Pyramid
Classifier: Intended Audience :: Developers
Classifier: License :: OSI Approved
Classifier: License :: OSI Approved :: Zope Public License
Classifier: Natural Language :: English
Classifier: Operating System :: OS Independent
Classifier: Programming Language :: Python
Classifier: Programming Language :: Python :: 3
Classifier: Programming Language :: Python :: 3.7
Classifier: Programming Language :: Python :: 3.8
Classifier: Programming Language :: Python :: 3.9
Classifier: Programming Language :: Python :: 3.10
Classifier: Programming Language :: Python :: 3.11
Classifier: Programming Language :: Python :: Implementation
Classifier: Programming Language :: Python :: Implementation :: CPython
Classifier: Topic :: Database
Classifier: Topic :: Software Development :: Libraries
Classifier: Topic :: Software Development :: Libraries :: Python Modules
Requires-Python: >=3.7
License-File: LICENSE.txt
Requires-Dist: SQLAlchemy <2,>=1.0
Requires-Dist: alembic >=0.7
Requires-Dist: pytz
Requires-Dist: setuptools
Requires-Dist: transaction
Requires-Dist: zope.component >=4.0.1
Requires-Dist: zope.interface
Requires-Dist: zope.sqlalchemy >=1.3
Provides-Extra: pyramid
Requires-Dist: pyramid ; extra == 'pyramid'
Provides-Extra: self-test
Requires-Dist: mock ; extra == 'self-test'
Requires-Dist: pyramid ; extra == 'self-test'
Requires-Dist: pytest ; extra == 'self-test'
Provides-Extra: test
Requires-Dist: gocept.testdb ; extra == 'test'
